[{"angY":152.12,"angX":180,"accZ":1.82,"accY":12.55,"accX":19.86,"velZ":197.27,"velY":176.27,"velX":124.82,"angZ":0.38},{"angY":154.41,"angX":180,"accZ":2.68,"accY":13.48,"accX":19.24,"velZ":241.39,"velY":165.83,"velX":200.68,"angZ":6.28},{"angY":156.09,"angX":180,"accZ":4.93,"accY":13.48,"accX":19.24,"velZ":257.81,"velY":153.38,"velX":241.58,"angZ":9.03},{"angY":158.05,"angX":180,"accZ":7.02,"accY":13.11,"accX":18.8,"velZ":264.77,"velY":136.84,"velX":282.9,"angZ":11.49},{"angY":160.25,"angX":180,"accZ":9.14,"accY":12.57,"accX":18.44,"velZ":267.94,"velY":116.39,"velX":323,"angZ":13.56},{"angY":162.6,"angX":180,"accZ":10.93,"accY":11.91,"accX":18.36,"velZ":264.83,"velY":92.77,"velX":360.53,"angZ":15.19},{"angY":165.01,"angX":180,"accZ":12.58,"accY":11.36,"accX":18.47,"velZ":255.92,"velY":67.2,"velX":394.47,"angZ":16.33},{"angY":167.38,"angX":180,"accZ":13.92,"accY":10.74,"accX":18.63,"velZ":241.39,"velY":41.2,"velX":424.07,"angZ":16.98},{"angY":169.66,"angX":180,"accZ":15.07,"accY":10.13,"accX":18.94,"velZ":228.64,"velY":15.32,"velX":448.73,"angZ":17.18},{"angY":173.83,"angX":180,"accZ":16.37,"accY":8.63,"accX":20.07,"velZ":205.81,"velY":33.81,"velX":481.26,"angZ":16.29},{"angY":175.57,"angX":180,"accZ":16.04,"accY":8.06,"accX":20.39,"velZ":192.08,"velY":55.54,"velX":489.5,"angZ":15.31},{"angY":177.06,"angX":180,"accZ":15,"accY":7.3,"accX":20.82,"velZ":180.54,"velY":75.74,"velX":492.49,"angZ":14.04},{"angY":178.24,"angX":180,"accZ":14.42,"accY":7.23,"accX":20.34,"velZ":167.18,"velY":93.75,"velX":490.3,"angZ":12.53},{"angY":179.13,"angX":180,"accZ":12.59,"accY":5.94,"accX":20.82,"velZ":156.68,"velY":109.68,"velX":484.19,"angZ":10.83},{"angY":179.66,"angX":180,"accZ":11.87,"accY":6.27,"accX":19.56,"velZ":140.81,"velY":123.05,"velX":473.94,"angZ":9.04},{"angY":179.87,"angX":180,"accZ":10.44,"accY":6.22,"accX":18.74,"velZ":128.23,"velY":135.38,"velX":460.57,"angZ":7.19},{"angY":179.84,"angX":180,"accZ":9.25,"accY":6.82,"accX":18.02,"velZ":126.53,"velY":147.77,"velX":443.48,"angZ":5.24},{"angY":179.61,"angX":180,"accZ":7.66,"accY":6.79,"accX":18.77,"velZ":132.69,"velY":160.22,"velX":423.65,"angZ":3.18},{"angY":179.13,"angX":180,"accZ":6.83,"accY":6.63,"accX":19.34,"velZ":130.68,"velY":170.9,"velX":401.79,"angZ":1.08},{"angY":178.38,"angX":180,"accZ":5.57,"accY":6.78,"accX":19.16,"velZ":118.1,"velY":178.41,"velX":377.99,"angZ":0.92},{"angY":177.39,"angX":180,"accZ":3.78,"accY":6.72,"accX":19.35,"velZ":107.79,"velY":184.14,"velX":353.09,"angZ":2.81},{"angY":176.17,"angX":180,"accZ":2.41,"accY":6.82,"accX":19.13,"velZ":87.89,"velY":186.83,"velX":327.58,"angZ":4.48},{"angY":174.77,"angX":180,"accZ":1.09,"accY":7.12,"accX":18.11,"velZ":66.59,"velY":187.01,"velX":301.7,"angZ":5.88},{"angY":173.25,"angX":180,"accZ":0.04,"accY":7.36,"accX":17.89,"velZ":56.46,"velY":186.65,"velX":275.21,"angZ":7.12},{"angY":171.68,"angX":180,"accZ":0.48,"accY":7.32,"accX":17.71,"velZ":50.42,"velY":185.61,"velX":248.35,"angZ":8.23},{"angY":170.06,"angX":180,"accZ":1.18,"accY":7.18,"accX":17.82,"velZ":43.09,"velY":183.41,"velX":221.37,"angZ":9.21},{"angY":168.41,"angX":180,"accZ":1.92,"accY":6.73,"accX":17.53,"velZ":36.13,"velY":180.24,"velX":194.52,"angZ":10.04},{"angY":165.12,"angX":180,"accZ":2.54,"accY":6.79,"accX":17.22,"velZ":18.68,"velY":171.45,"velX":142.15,"angZ":11.28},{"angY":139.19,"angX":180,"accZ":1.09,"accY":6.01,"accX":12.61,"velZ":66.65,"velY":97.23,"velX":123.05,"angZ":2.71},{"angY":138.09,"angX":180,"accZ":1.38,"accY":6.07,"accX":12.29,"velZ":64.51,"velY":97.6,"velX":125.43,"angZ":2.17},{"angY":135.88,"angX":180,"accZ":2.06,"accY":6.12,"accX":12.38,"velZ":58.65,"velY":98.51,"velX":127.44,"angZ":1.24},{"angY":134.79,"angX":180,"accZ":2.46,"accY":6.21,"accX":12.3,"velZ":52,"velY":98.75,"velX":127.56,"angZ":0.92},{"angY":133.72,"angX":180,"accZ":2.8,"accY":6.18,"accX":12.29,"velZ":43.27,"velY":99.06,"velX":127.2,"angZ":0.74},{"angY":132.67,"angX":180,"accZ":3.11,"accY":6.08,"accX":12.25,"velZ":33.81,"velY":99.12,"velX":126.28,"angZ":0.72},{"angY":131.67,"angX":180,"accZ":3.34,"accY":6.11,"accX":12.37,"velZ":22.4,"velY":99,"velX":125.06,"angZ":0.89},{"angY":130.7,"angX":180,"accZ":3.6,"accY":6.27,"accX":12.55,"velZ":11.54,"velY":98.51,"velX":123.47,"angZ":1.25},{"angY":129.79,"angX":180,"accZ":3.79,"accY":6.28,"accX":12.64,"velZ":2.62,"velY":97.47,"velX":121.4,"angZ":1.78},{"angY":140.02,"angX":180,"accZ":0.59,"accY":8.31,"accX":10.97,"velZ":111.45,"velY":34.73,"velX":123.41,"angZ":40.78},{"angY":139.38,"angX":180,"accZ":0.94,"accY":8.36,"accX":10.95,"velZ":108.95,"velY":30.64,"velX":126.59,"angZ":42},{"angY":138.83,"angX":180,"accZ":1.27,"accY":8.18,"accX":11.27,"velZ":105.47,"velY":26.49,"velX":129.52,"angZ":43.24},{"angY":138.36,"angX":180,"accZ":1.43,"accY":7.89,"accX":11.09,"velZ":102.78,"velY":22.34,"velX":131.84,"angZ":44.48},{"angY":134.58,"angX":180,"accZ":0.41,"accY":10.01,"accX":10.26,"velZ":17.33,"velY":49.01,"velX":130,"angZ":47.41},{"angY":134.1,"angX":180,"accZ":0.68,"accY":10.09,"accX":10.42,"velZ":23.74,"velY":45.9,"velX":130.43,"angZ":47.7},{"angY":133.24,"angX":180,"accZ":1.34,"accY":10.25,"accX":10.32,"velZ":49.99,"velY":40.59,"velX":129.94,"angZ":48.91},{"angY":132.87,"angX":180,"accZ":1.85,"accY":10.25,"accX":10.16,"velZ":61.83,"velY":37.54,"velX":129.39,"angZ":49.82}]