[{"angY":52.03,"angX":180,"accZ":2.9,"accY":2.37,"accX":13.23,"velZ":19.47,"velY":42.97,"velX":120.3,"angZ":120.51},{"angY":51.53,"angX":180,"accZ":2.96,"accY":2.57,"accX":12.9,"velZ":23.56,"velY":44.31,"velX":121.22,"angZ":120.66},{"angY":51,"angX":180,"accZ":3.04,"accY":2.68,"accX":12.56,"velZ":26.12,"velY":45.78,"velX":121.77,"angZ":120.77},{"angY":50.47,"angX":180,"accZ":3.07,"accY":2.81,"accX":12.28,"velZ":26.37,"velY":47.36,"velX":121.89,"angZ":120.87},{"angY":49.93,"angX":180,"accZ":3.14,"accY":2.81,"accX":12.11,"velZ":23.5,"velY":49.13,"velX":121.7,"angZ":121},{"angY":49.41,"angX":180,"accZ":3.18,"accY":2.76,"accX":12.19,"velZ":17.94,"velY":51.09,"velX":121.22,"angZ":121.2},{"angY":48.89,"angX":180,"accZ":3.3,"accY":2.62,"accX":12.27,"velZ":12.39,"velY":53.1,"velX":120.54,"angZ":121.46},{"angY":40.13,"angX":180,"accZ":2.64,"accY":5.45,"accX":13.65,"velZ":11.41,"velY":34.18,"velX":120.3,"angZ":133.39},{"angY":40.5,"angX":180,"accZ":2.25,"accY":6.06,"accX":13.89,"velZ":15.38,"velY":36.62,"velX":121.64,"angZ":133.18},{"angY":40.91,"angX":180,"accZ":1.82,"accY":6.63,"accX":13.94,"velZ":19.9,"velY":39.49,"velX":123.29,"angZ":132.97},{"angY":41.37,"angX":180,"accZ":1.55,"accY":6.79,"accX":13.99,"velZ":24.84,"velY":42.48,"velX":125.31,"angZ":132.76},{"angY":41.9,"angX":180,"accZ":1.4,"accY":6.99,"accX":13.73,"velZ":30.88,"velY":45.72,"velX":127.44,"angZ":132.56},{"angY":42.47,"angX":180,"accZ":1.25,"accY":7.29,"accX":13.35,"velZ":33.81,"velY":48.77,"velX":129.64,"angZ":132.32},{"angY":43.04,"angX":180,"accZ":1.18,"accY":6.94,"accX":13.01,"velZ":32.96,"velY":51.51,"velX":131.9,"angZ":132.02},{"angY":43.62,"angX":180,"accZ":1.14,"accY":6.31,"accX":13.42,"velZ":33.02,"velY":53.89,"velX":133.91,"angZ":131.68},{"angY":44.23,"angX":180,"accZ":0.93,"accY":5.71,"accX":14.45,"velZ":35.71,"velY":56.58,"velX":135.25,"angZ":131.3},{"angY":44.89,"angX":180,"accZ":0.45,"accY":5.71,"accX":15.49,"velZ":40.65,"velY":60.06,"velX":136.05,"angZ":130.89},{"angY":45.6,"angX":180,"accZ":0.09,"accY":5.82,"accX":15.45,"velZ":44.62,"velY":64.27,"velX":136.6,"angZ":130.42},{"angY":46.96,"angX":180,"accZ":1,"accY":6.16,"accX":15.48,"velZ":35.83,"velY":71.96,"velX":138.06,"angZ":129.17},{"angY":47.54,"angX":180,"accZ":0.39,"accY":5.67,"accX":17.72,"velZ":28.26,"velY":75.81,"velX":138.67,"angZ":128.34},{"angY":48.11,"angX":180,"accZ":0.06,"accY":6.06,"accX":17.26,"velZ":27.95,"velY":80.81,"velX":138.85,"angZ":127.4},{"angY":48.66,"angX":180,"accZ":0.49,"accY":6.65,"accX":16.09,"velZ":26.25,"velY":85.63,"velX":139.34,"angZ":126.34},{"angY":49.16,"angX":180,"accZ":0.86,"accY":6.34,"accX":15.72,"velZ":22.89,"velY":89.29,"velX":140.14,"angZ":125.17},{"angY":49.67,"angX":180,"accZ":0.97,"accY":6.07,"accX":15.51,"velZ":26.43,"velY":92.29,"velX":140.56,"angZ":123.93},{"angY":50.25,"angX":180,"accZ":0.97,"accY":5.77,"accX":15.34,"velZ":35.83,"velY":94.97,"velX":140.5,"angZ":122.63},{"angY":50.89,"angX":180,"accZ":0.88,"accY":5.32,"accX":15.04,"velZ":45.17,"velY":97.41,"velX":139.83,"angZ":121.29},{"angY":51.56,"angX":180,"accZ":0.98,"accY":5.08,"accX":14.75,"velZ":51.21,"velY":99.43,"velX":138.55,"angZ":119.86},{"angY":52.19,"angX":180,"accZ":1.3,"accY":4.96,"accX":14.41,"velZ":51.33,"velY":100.83,"velX":136.78,"angZ":118.34},{"angY":52.73,"angX":180,"accZ":1.82,"accY":4.98,"accX":14.18,"velZ":47.36,"velY":101.56,"velX":134.83,"angZ":116.75},{"angY":53.21,"angX":180,"accZ":2.22,"accY":4.98,"accX":14.03,"velZ":45.41,"velY":101.56,"velX":132.87,"angZ":115.09},{"angY":53.66,"angX":180,"accZ":2.58,"accY":4.68,"accX":13.97,"velZ":47.12,"velY":101.26,"velX":130.92,"angZ":113.39},{"angY":54.11,"angX":180,"accZ":2.85,"accY":4.42,"accX":14.06,"velZ":51.57,"velY":100.77,"velX":128.66,"angZ":111.63},{"angY":54.59,"angX":180,"accZ":3.18,"accY":4.06,"accX":13.99,"velZ":59.75,"velY":100.16,"velX":125.98,"angZ":109.82},{"angY":55.13,"angX":180,"accZ":3.63,"accY":3.75,"accX":14.05,"velZ":70.56,"velY":99.49,"velX":122.74,"angZ":107.93}]